dbvirus_searcher/__init__.py
dbvirus_searcher/__main__.py
dbvirus_searcher/searcher.py
dbvirus_searcher-0.1.1.dist-info/LICENSE
dbvirus_searcher-0.1.1.dist-info/WHEEL
dbvirus_searcher-0.1.1.dist-info/METADATA
dbvirus_searcher-0.1.1.dist-info/RECORD
